<?xml version="1.0" encoding="UTF-8" standalone="no" ?>
<subtitles tracks="3">
	<subtitle>
		<time>46</time>
		<track1>hello</track1>
		<track2>您好</track2>
		<track3>nín hǎo</track3>
	</subtitle>
	<subtitle>
		<time>56</time>
		<track1>hello I am not feeling too well</track1>
		<track2>您好 我有点儿不舒服</track2>
		<track3>nín hǎo wǒ yǒu diǎnr bù shūfu</track3>
	</subtitle>
	<subtitle>
		<time>82</time>
		<track1>what is the matter</track1>
		<track2>哪里不舒服</track2>
		<track3>nǎlǐ bù shūfu</track3>
	</subtitle>
	<subtitle>
		<time>98</time>
		<track1>I have got a stomach ache</track1>
		<track2>我有点儿胃疼</track2>
		<track3>wǒ yǒu diǎnr wèiténg</track3>
	</subtitle>
	<subtitle>
		<time>108</time>
		<track1>I also suffer from diarrhea</track1>
		<track2>还有点儿腹泻</track2>
		<track3>háiyǒu diǎnr fùxiè</track3>
	</subtitle>
	<subtitle>
		<time>124</time>
		<track1>how long did you been suffering from it</track1>
		<track2>多长时间了</track2>
		<track3>duō cháng shíjiān le</track3>
	</subtitle>
	<subtitle>
		<time>138</time>
		<track1>for two days</track1>
		<track2>两天了</track2>
		<track3>liǎng tiān le</track3>
	</subtitle>
	<subtitle>
		<time>148</time>
		<track1></track1>
		<track2></track2>
		<track3></track3>
	</subtitle>	
	<subtitle>
		<time>156</time>
		<track1>here some medicine for you it has good therapeutical properties</track1>
		<track2>这是给您的药  疗效很好</track2>
		<track3>zhè shì gěi nín de yào liáoxiào hěn hǎo</track3>
	</subtitle>
	<subtitle>
		<time>184</time>
		<track1>ok I will try it</track1>
		<track2>好的 我试试</track2>
		<track3>hǎo de wǒ shìshi</track3>
	</subtitle>	
	<subtitle>
		<time>212</time>
		<track1>how many times a day</track1>
		<track2>一天吃几次?</track2>
		<track3>yī tiān chī jǐ cì</track3>
	</subtitle>
	<subtitle>
		<time>226</time>
		<track1>three times a day after meals</track1>
		<track2>一天三次, 饭后吃</track2>
		<track3>yī tiān sān cì fàn hòu chī</track3>
	</subtitle>
	<subtitle>
		<time>256</time>
		<track1>ok  how much is it</track1>
		<track2>好的 多少钱</track2>
		<track3>hǎo de duōshǎo qián</track3>
	</subtitle>
	<subtitle>
		<time>264</time>
		<track1>10 Yuan</track1>
		<track2>十元钱</track2>
		<track3>shí yuán qián</track3>
	</subtitle>
	<subtitle>
		<time>268</time>
		<track1>ok here is the money</track1>
		<track2>好</track2>
		<track3>hǎo</track3>
	</subtitle>	
	<subtitle>
		<time>292</time>
		<track1>ok here is the money</track1>
		<track2>给您的钱</track2>
		<track3>gěi nín de qián</track3>
	</subtitle>		
	<subtitle>
		<time>308</time>
		<track1>thank you hope you feel better soon  good bye</track1>
		<track2>谢谢 祝您早日康复  再见</track2>
		<track3>xièxie zhù nín zǎorì kāngfù zàijiàn</track3>
	</subtitle>
	<subtitle>
		<time>338</time>
		<track1>ok thank you</track1>
		<track2>好的 谢谢</track2>
		<track3>hǎo de xièxie</track3>
	</subtitle>
	<subtitle>
		<time>348</time>
		<track1></track1>
		<track2></track2>
		<track3></track3>
	</subtitle>
</subtitles>
